LICENSE
README.md
pyproject.toml
setup.cfg
setup.py
fulu/__init__.py
fulu/_base_aug.py
fulu/bnn_aug.py
fulu/gp_aug.py
fulu/mlp_reg_aug.py
fulu/nf_aug.py
fulu/plotting.py
fulu/single_layer_aug.py
fulu.egg-info/PKG-INFO
fulu.egg-info/SOURCES.txt
fulu.egg-info/dependency_links.txt
fulu.egg-info/requires.txt
fulu.egg-info/top_level.txt