Metadata-Version: 2.1
Name: fulu
Version: 0.1.1
Summary: Light curve approximation and augmentation
Home-page: https://github.com/HSE-LAMBDA/fulu
Author: Mikhail Hushchyn
Author-email: mhushchyn@hse.ru
License: MIT
Keywords: science,astrophysics
Platform: UNKNOWN
Classifier: Intended Audience :: Science/Research
Classifier: License :: OSI Approved :: MIT License
Classifier: Topic :: Scientific/Engineering :: Astronomy
Classifier: Programming Language :: Python :: 3
License-File: LICENSE
